_bbfreeze_loader/consolew
_bbfreeze_loader/console
_bbfreeze_loader
