Metadata-Version: 1.1
Name: bbfreeze-loader
Version: 1.1.0
Summary: provide binary loaders for bbfreeze
Home-page: http://pypi.python.org/pypi/bbfreeze/
Author: Ralf Schmitt
Author-email: ralf@systemexit.de
License: zlib/libpng license
Platform: Linux Windows
Classifier: Development Status :: 5 - Production/Stable
Classifier: License :: OSI Approved :: zlib/libpng License
Classifier: Intended Audience :: Developers
Classifier: Programming Language :: Python
Classifier: Programming Language :: Python :: 2
Classifier: Programming Language :: Python :: 2.4
Classifier: Programming Language :: Python :: 2.5
Classifier: Programming Language :: Python :: 2.6
Classifier: Programming Language :: Python :: 2.7
Classifier: Topic :: Software Development :: Build Tools
Classifier: Topic :: System :: Software Distribution
